09-fulladdrer8b/fulladder8b.v
//Full adder
//1bit
//what happen in a full adder is that we have three inputs a,b,cin and two outputs as sum and cout
//truth table for full adder

// cin | a | b | sum | cout
//  0  | 0 | 0 |  0  |  0
//  0  | 0 | 1 |  1  |  0
//  0  | 1 | 0 |  1  |  0
//  0  | 1 | 1 |  0  |  1
//  1  | 0 | 0 |  1  |  0
//  1  | 0 | 1 |  0  |  1
//  1  | 1 | 0 |  0  |  1
//  1  | 1 | 1 |  1  |  1

//1bit full adder

module fulladder8b(
    input wire [7:0] a,
    input wire [7:0] b,
    input wire cin,
    output wire [7:0] s,
    output wire cout
);
    assign {cout,s}=a+b+cin;
endmodule

09-fulladdrer8b/tbfulladder1b.v
`timescale 1ns/1ps
`include "fulladder8b.v"

module tb();
    reg [7:0] a;
    reg [7:0] b;
    reg cin;
    wire [7:0] s;
    wire cout;


    fulladder8b uut(.a(a),.b(b),.cin(cin),.s(s),.cout(cout));

    initial begin
        $dumpfile("dump.vcd");
        $dumpvars(0,tb);

        a=8'b00000000; b=8'b00000000; cin=1'b0;
        #10; a=8'b00000000; b=8'b00000000; cin=1'b1;
        #10; a=8'b00000000; b=8'b00000001; cin=1'b0;
        #10; a=8'b00000000; b=8'b00000001; cin=1'b1;
        #10; a=8'b00000001; b=8'b00000000; cin=1'b0;
        #10; a=8'b00000001; b=8'b00000000; cin=1'b1;
        #10; a=8'b00000001; b=8'b00000001; cin=1'b0;
        #10; a=8'b00000001; b=8'b00000001; cin=1'b1;
        #10; a=8'b00000001; b=8'b00000010; cin=1'b0;
        #10; a=8'b00000001; b=8'b00000010; cin=1'b1;
        #10; a=8'b00000010; b=8'b00000000; cin=1'b0;
        #10; a=8'b00000010; b=8'b00000000; cin=1'b1;
        #10; a=8'b00000010; b=8'b00000001; cin=1'b0;    
        #10; a=8'b00000010; b=8'b00000001; cin=1'b1;
        #10; a=8'b00000010; b=8'b00000010; cin=1'b0;
        #10; a=8'b00000010; b=8'b00000010; cin=1'b1;
        #10; a=8'b00000010; b=8'b00000011; cin=1'b0;
        #10; a=8'b00000010; b=8'b00000011; cin=1'b1;



    end

    initial begin
      $monitor("a=%b | b=%b | cin=%b | s=%b | cout=%b", a, b, cin, s, cout);
    end

endmodule

09-fulladdrer8b/dump.vcd
$date
	Tue Apr 29 14:13:29 2025
$end
$version
	Icarus Verilog
$end
$timescale
	1ps
$end
$scope module tb $end
$var wire 8 ! s [7:0] $end
$var wire 1 " cout $end
$var reg 8 # a [7:0] $end
$var reg 8 $ b [7:0] $end
$var reg 1 % cin $end
$scope module uut $end
$var wire 8 & a [7:0] $end
$var wire 8 ' b [7:0] $end
$var wire 1 % cin $end
$var wire 8 ( s [7:0] $end
$var wire 1 " cout $end
$upscope $end
$upscope $end
$enddefinitions $end
$comment Show the parameter values. $end
$dumpall
$end
#0
$dumpvars
b0 (
b0 '
b0 &
0%
b0 $
b0 #
0"
b0 !
$end
#10000
b1 !
b1 (
1%
#20000
0%
b1 $
b1 '
#30000
b10 !
b10 (
1%
#40000
b1 !
b1 (
0%
b0 $
b0 '
b1 #
b1 &
#50000
b10 !
b10 (
1%
#60000
0%
b1 $
b1 '
#70000
b11 !
b11 (
1%
#80000
0%
b10 $
b10 '
#90000
b100 !
b100 (
1%
#100000
b10 !
b10 (
0%
b0 $
b0 '
b10 #
b10 &
#110000
b11 !
b11 (
1%
#120000
0%
b1 $
b1 '
#130000
b100 !
b100 (
1%
#140000
0%
b10 $
b10 '
#150000
b101 !
b101 (
1%
#160000
0%
b11 $
b11 '
#170000
b110 !
b110 (
1%
