11-dflipflop/dflipflop.v
`timescale  1ns/1ps
module dflipflop(
    input wire d,
    input wire clk,
    input wire en,
    input wire reset,
    output reg q
);
   always @(posedge clk or posedge reset) begin
        if(reset) q<=0;
        else if(en) begin
            q<=d;
        end
   end

endmodule

11-dflipflop/tb.v
`timescale 1ns/1ps
`include "dflipflop.v"


module tb();
    reg clk, d, en, reset;
    wire q;

    dflipflop uut(
        .d(d),
        .clk(clk),
        .en(en),
        .reset(reset),
        .q(q)
    );

    initial begin
        $dumpfile("dump.vcd");
        $dumpvars(0, tb);
    end


    initial begin
        clk = 0;
        forever #5 clk = ~clk;
    end

 
    initial begin
   
        d = 0; en = 0; reset = 0;

    
        #2 reset = 1;
        #8 reset = 0;

        #5 en = 1; d = 1;
        #10 d = 0;
        #10 en = 0;
        #10 d = 1;
        #10 en = 1;
        $finish;

    end

    initial begin
        $monitor("time=%0t | clk=%b | d=%b | en=%b | reset=%b | q=%b", $time, clk, d, en, reset, q);
       
    end

endmodule

11-dflipflop/tb.vcd
$date
	Tue May 20 14:36:25 2025
$end
$version
	Icarus Verilog
$end
$timescale
	1ps
$end
$scope module tb $end
$var wire 1 ! q $end
$var reg 1 " clk $end
$var reg 1 # d $end
$var reg 1 $ en $end
$var reg 1 % reset $end
$scope module uut $end
$var wire 1 " clk $end
$var wire 1 # d $end
$var wire 1 $ en $end
$var wire 1 % reset $end
$var reg 1 ! q $end
$upscope $end
$upscope $end
$enddefinitions $end
$comment Show the parameter values. $end
$dumpall
$end
#0
$dumpvars
0%
0$
0#
0"
x!
$end
#2000
0!
1%
#5000
1"
#10000
0"
0%
#15000
1!
1"
1#
1$
#20000
0"
#25000
0!
1"
0#
#30000
0"
#35000
1"
0$
#40000
0"
#45000
1"
1#
#50000
0"
#55000
1!
1"
1$
