09-fulladdrer/fulladder.v
//Full adder
//1bit
//what happen in a full adder is that we have three inputs a,b,cin and two outputs as sum and cout
//truth table for full adder

// cin | a | b | sum | cout
//  0  | 0 | 0 |  0  |  0
//  0  | 0 | 1 |  1  |  0
//  0  | 1 | 0 |  1  |  0
//  0  | 1 | 1 |  0  |  1
//  1  | 0 | 0 |  1  |  0
//  1  | 0 | 1 |  0  |  1
//  1  | 1 | 0 |  0  |  1
//  1  | 1 | 1 |  1  |  1

//1bit full adder

module fulladder1b(
    input wire a,
    input wire b,
    input wire cin,
    output wire s,
    input wire cout
);

    assign {cout,s}=a+b+cin;
endmodule

09-fulladdrer/tbfulladder1b.v
`timescale 1ns/1ps
`include "fulladder.v"

module tb();
    reg a;
    reg b;
    reg cin;
    wire s;
    wire cout;


    fulladder1b uut(.a(a),.b(b),.cin(cin),.s(s),.cout(cout));

    initial begin
        $dumpfile("dump.vcd");
        $dumpvars(0,tb);

             a=1'b0; b=1'b0; cin=1'b0;
        #10; a=1'b0; b=1'b0; cin=1'b1;
        #10; a=1'b0; b=1'b1; cin=1'b0;
        #10; a=1'b0; b=1'b1; cin=1'b1;

        #10; a=1'b1; b=1'b0; cin=1'b0;
        #10; a=1'b1; b=1'b0; cin=1'b1;
        #10; a=1'b1; b=1'b1; cin=1'b0;
        #10; a=1'b1; b=1'b1; cin=1'b1;
    end

    initial begin
      $monitor("a=%b | b=%b | cin=%b | s=%b | cout=%b", a, b, cin, s, cout);
    end

endmodule

09-fulladdrer/dump.vcd
$date
	Tue Apr 29 14:07:22 2025
$end
$version
	Icarus Verilog
$end
$timescale
	1ps
$end
$scope module tb $end
$var wire 1 ! s $end
$var wire 1 " cout $end
$var reg 1 # a $end
$var reg 1 $ b $end
$var reg 1 % cin $end
$scope module uut $end
$var wire 1 # a $end
$var wire 1 $ b $end
$var wire 1 % cin $end
$var wire 1 ! s $end
$var wire 1 " cout $end
$upscope $end
$upscope $end
$enddefinitions $end
$comment Show the parameter values. $end
$dumpall
$end
#0
$dumpvars
0%
0$
0#
0"
0!
$end
#10000
1!
1%
#20000
0%
1$
#30000
0!
1"
1%
#40000
0"
1!
0%
0$
1#
#50000
0!
1"
1%
#60000
0%
1$
#70000
1!
1%
