14-fsm_moor/fsm_moor.v
module divideby3 (
    input clk,
    input reset,
    output reg y
);

    reg [1:0] state, nextstate;

    parameter S0 = 2'b00;
    parameter S1 = 2'b01;
    parameter S2 = 2'b10;

    // State register
    always @(posedge clk or posedge reset) begin
        if (reset)
            state <= S0;
        else
            state <= nextstate;
    end

    // Next state logic
    always @(*) begin
        case (state)
            S0: nextstate = S1;
            S1: nextstate = S2;
            S2: nextstate = S0;
            default: nextstate = S0;
        endcase
    end

    // Output logic: pulse high once every 3 cycles
    always @(posedge clk or posedge reset) begin
        if (reset)
            y <= 0;
        else
            y <= (state == S0);  // high only in state S0
    end

endmodule

14-fsm_moor/tb.v
`timescale 1ns / 1ps
`include "fsm_moor.v"
module tb();

    // Inputs
    reg clk;
    reg reset;

    // Output
    wire y;

    // Instantiate the Unit Under Test (UUT)
    divideby3 uut (
        .clk(clk),
        .reset(reset),
        .y(y)
    );
    initial begin
        // Initialize the dump file for waveform viewing
        $dumpfile("fsm_moor.vcd");
        $dumpvars(0, tb);
    end

    // Clock generation: 10ns period => 100MHz
    initial begin
        clk = 0;
        forever #5 clk = ~clk;  // Toggle clock every 5 ns
    end

    // Stimulus
    initial begin
        // Initialize reset
        reset = 1;
        #20;            // Hold reset high for 20 ns
        reset = 0;

        // Run simulation for some time
        #200;

        // Finish simulation
        $finish;
    end

    // Monitor outputs
    initial begin
        $display("Time\tclk\treset\ty");
        $monitor("%0t\t%b\t%b\t%b", $time, clk, reset, y);
    end

endmodule

14-fsm_moor/fsm_moor.vcd
$date
	Tue May 27 15:37:02 2025
$end
$version
	Icarus Verilog
$end
$timescale
	1ps
$end
$scope module tb $end
$var wire 1 ! y $end
$var reg 1 " clk $end
$var reg 1 # reset $end
$scope module uut $end
$var wire 1 " clk $end
$var wire 1 # reset $end
$var parameter 2 $ S0 $end
$var parameter 2 % S1 $end
$var parameter 2 & S2 $end
$var reg 2 ' nextstate [1:0] $end
$var reg 2 ( state [1:0] $end
$var reg 1 ! y $end
$upscope $end
$upscope $end
$enddefinitions $end
$comment Show the parameter values. $end
$dumpall
b10 &
b1 %
b0 $
$end
#0
$dumpvars
b0 (
b1 '
1#
0"
0!
$end
#5000
1"
#10000
0"
#15000
1"
#20000
0"
0#
#25000
b10 '
1!
b1 (
1"
#30000
0"
#35000
b0 '
b10 (
0!
1"
#40000
0"
#45000
b1 '
b0 (
1"
#50000
0"
#55000
b10 '
b1 (
1!
1"
#60000
0"
#65000
b0 '
0!
b10 (
1"
#70000
0"
#75000
b1 '
b0 (
1"
#80000
0"
#85000
b10 '
1!
b1 (
1"
#90000
0"
#95000
b0 '
b10 (
0!
1"
#100000
0"
#105000
b1 '
b0 (
1"
#110000
0"
#115000
b10 '
b1 (
1!
1"
#120000
0"
#125000
b0 '
0!
b10 (
1"
#130000
0"
#135000
b1 '
b0 (
1"
#140000
0"
#145000
b10 '
1!
b1 (
1"
#150000
0"
#155000
b0 '
b10 (
0!
1"
#160000
0"
#165000
b1 '
b0 (
1"
#170000
0"
#175000
b10 '
b1 (
1!
1"
#180000
0"
#185000
b0 '
0!
b10 (
1"
#190000
0"
#195000
b1 '
b0 (
1"
#200000
0"
#205000
b10 '
1!
b1 (
1"
#210000
0"
#215000
b0 '
b10 (
0!
1"
